correlation/__init__.py
correlation/analytic.py
correlation/numeric.py
correlation/result.py
correlation/utils.py
tests/__init__.py
tests/test_analytic.py
tests/test_numeric.py
correlation_analysis-0.1.0.dist-info/LICENSE
correlation_analysis-0.1.0.dist-info/METADATA
correlation_analysis-0.1.0.dist-info/WHEEL
correlation_analysis-0.1.0.dist-info/top_level.txt
correlation_analysis-0.1.0.dist-info/RECORD
