Metadata-Version: 2.1
Name: correlation-analysis
Version: 0.1.0
Summary: High order correlation analysis of error models.
Author: Yiming Zhang
Requires-Python: >=3.7
License-File: LICENSE
Requires-Dist: numpy
Requires-Dist: scipy
Requires-Dist: stim
Provides-Extra: dev
Requires-Dist: pytest ; extra == 'dev'
Requires-Dist: ruff ; extra == 'dev'
